<?xml version="1.0"?>
<!DOCTYPE hibernate-mapping PUBLIC "-//Hibernate/Hibernate Mapping DTD 3.0//EN"
"http://www.hibernate.org/dtd/hibernate-mapping-3.0.dtd">
<!-- Generated Feb 28, 2014 5:25:41 PM by Hibernate Tools 3.4.0.CR1 -->
<hibernate-mapping>
    <class name="edu.pitt.sis.exp.colfusion.persistence.orm.ColfusionCategories" table="colfusion_categories" catalog="colfusion">
        <id name="categoryAutoId" type="java.lang.Integer">
            <column name="category__auto_id" />
            <generator class="identity" />
        </id>
        <property name="categoryLang" type="string">
            <column name="category_lang" length="2" />
        </property>
        <property name="categoryId" type="int">
            <column name="category_id" not-null="true" />
        </property>
        <property name="categoryParent" type="int">
            <column name="category_parent" not-null="true" />
        </property>
        <property name="categoryName" type="string">
            <column name="category_name" length="64" />
        </property>
        <property name="categorySafeName" type="string">
            <column name="category_safe_name" length="64" />
        </property>
        <property name="rgt" type="int">
            <column name="rgt" not-null="true" />
        </property>
        <property name="lft" type="int">
            <column name="lft" not-null="true" />
        </property>
        <property name="categoryEnabled" type="int">
            <column name="category_enabled" not-null="true" />
        </property>
        <property name="categoryOrder" type="int">
            <column name="category_order" not-null="true" />
        </property>
        <property name="categoryDesc" type="string">
            <column name="category_desc" />
        </property>
        <property name="categoryKeywords" type="string">
            <column name="category_keywords" />
        </property>
        <property name="categoryAuthorLevel" type="string">
            <column name="category_author_level" length="7" not-null="true" />
        </property>
        <property name="categoryAuthorGroup" type="string">
            <column name="category_author_group" />
        </property>
        <property name="categoryVotes" type="string">
            <column name="category_votes" length="4" not-null="true" />
        </property>
        <property name="categoryKarma" type="string">
            <column name="category_karma" length="4" not-null="true" />
        </property>
    </class>
</hibernate-mapping>
