<?xml version="1.0"?>
<!DOCTYPE hibernate-mapping PUBLIC "-//Hibernate/Hibernate Mapping DTD 3.0//EN"
"http://hibernate.sourceforge.net/hibernate-mapping-3.0.dtd">
<!-- Generated 2014-6-10 16:18:00 by Hibernate Tools 3.4.0.CR1 -->
<hibernate-mapping>
    <class name="edu.pitt.sis.exp.colfusion.persistence.orm.ColfusionLinks" table="colfusion_links" catalog="colfusion2.0">
        <id name="linkId" type="int">
            <column name="link_id" />
            <generator class="assigned" />
        </id>
        <property name="linkAuthor" type="int">
            <column name="link_author" not-null="true" />
        </property>
        <property name="linkStatus" type="string">
            <column name="link_status" length="9" />
        </property>
        <property name="linkRandkey" type="int">
            <column name="link_randkey" not-null="true" />
        </property>
        <property name="linkVotes" type="int">
            <column name="link_votes" not-null="true" />
        </property>
        <property name="linkReports" type="int">
            <column name="link_reports" not-null="true" />
        </property>
        <property name="linkComments" type="int">
            <column name="link_comments" not-null="true" />
        </property>
        <property name="linkKarma" type="big_decimal">
            <column name="link_karma" precision="10" not-null="true" />
        </property>
        <property name="linkModified" type="timestamp">
            <column name="link_modified" length="19" not-null="true" />
        </property>
        <property name="linkDate" type="timestamp">
            <column name="link_date" length="19" not-null="true" />
        </property>
        <property name="linkPublishedDate" type="timestamp">
            <column name="link_published_date" length="19" not-null="true" />
        </property>
        <property name="linkCategory" type="int">
            <column name="link_category" not-null="true" />
        </property>
        <property name="linkLang" type="int">
            <column name="link_lang" not-null="true" />
        </property>
        <property name="linkUrl" type="string">
            <column name="link_url" length="200" />
        </property>
        <property name="linkUrlTitle" type="string">
            <column name="link_url_title" length="65535" />
        </property>
        <property name="linkTitle" type="string">
            <column name="link_title" length="65535" />
        </property>
        <property name="linkTitleUrl" type="string">
            <column name="link_title_url" />
        </property>
        <property name="linkContent" type="string">
            <column name="link_content" length="16777215" />
        </property>
        <property name="linkSummary" type="string">
            <column name="link_summary" length="65535" />
        </property>
        <property name="linkTags" type="string">
            <column name="link_tags" length="65535" />
        </property>
        <property name="linkField1" type="string">
            <column name="link_field1" />
        </property>
        <property name="linkField2" type="string">
            <column name="link_field2" />
        </property>
        <property name="linkField3" type="string">
            <column name="link_field3" />
        </property>
        <property name="linkField4" type="string">
            <column name="link_field4" />
        </property>
        <property name="linkField5" type="string">
            <column name="link_field5" />
        </property>
        <property name="linkField6" type="string">
            <column name="link_field6" />
        </property>
        <property name="linkField7" type="string">
            <column name="link_field7" />
        </property>
        <property name="linkField8" type="string">
            <column name="link_field8" />
        </property>
        <property name="linkField9" type="string">
            <column name="link_field9" />
        </property>
        <property name="linkField10" type="string">
            <column name="link_field10" />
        </property>
        <property name="linkField11" type="string">
            <column name="link_field11" />
        </property>
        <property name="linkField12" type="string">
            <column name="link_field12" />
        </property>
        <property name="linkField13" type="string">
            <column name="link_field13" />
        </property>
        <property name="linkField14" type="string">
            <column name="link_field14" />
        </property>
        <property name="linkField15" type="string">
            <column name="link_field15" />
        </property>
        <property name="linkGroupId" type="int">
            <column name="link_group_id" not-null="true" />
        </property>
        <property name="linkGroupStatus" type="string">
            <column name="link_group_status" length="9" not-null="true" />
        </property>
        <property name="linkOut" type="int">
            <column name="link_out" not-null="true" />
        </property>
    </class>
</hibernate-mapping>
