<?xml version="1.0"?>
<!DOCTYPE hibernate-mapping PUBLIC "-//Hibernate/Hibernate Mapping DTD 3.0//EN"
"http://hibernate.sourceforge.net/hibernate-mapping-3.0.dtd">
<!-- Generated 2014-6-10 16:18:00 by Hibernate Tools 3.4.0.CR1 -->
<hibernate-mapping>
    <class name="edu.pitt.sis.exp.colfusion.persistence.orm.ColfusionValidationCode" table="colfusion_validation_code" catalog="colfusion">
        <composite-id name="id" class="edu.pitt.sis.exp.colfusion.persistence.orm.ColfusionValidationCodeId">
            <key-property name="email" type="string">
                <column name="email" length="100" />
            </key-property>
            <key-property name="vcode" type="string">
                <column name="vcode" length="20" />
            </key-property>
            <key-property name="isUsed" type="boolean">
                <column name="isUsed" />
            </key-property>
        </composite-id>
    </class>
</hibernate-mapping>
